{"assets":{"9C11DC258698772E4D281BEEDA3F6C41":{"type":"texture","index":2,"assetRequest":{"type":"slide","state":"contents","slide":"none"},"url":{"native":"assets/3F550030-6477-4261-9B31-014C97946240.pdf"},"width":633,"height":710},"55C7C75F7F86095E359F538B6151452D":{"type":"texture","index":3,"assetRequest":{"type":"slide","state":"contents","slide":"none"},"url":{"native":"assets/3F550030-6477-4261-9B31-014C97946240.pdf"},"width":479,"height":38},"B5EBA366585F3093799141C416FC9441":{"type":"texture","index":1,"assetRequest":{"type":"slide","state":"contents","slide":"none"},"url":{"native":"assets/3F550030-6477-4261-9B31-014C97946240.pdf"},"width":43,"height":23},"3C900D25C5F715D1A9BDACCFBFC181F4":{"type":"texture","index":4,"assetRequest":{"type":"slide","state":"contents","slide":"none"},"url":{"native":"assets/3F550030-6477-4261-9B31-014C97946240.pdf"},"width":1387,"height":778},"F40AA37D961CB1662EDB770BB1B02315":{"type":"texture","index":5,"assetRequest":{"type":"slide","state":"contents","slide":"none"},"url":{"native":"assets/3F550030-6477-4261-9B31-014C97946240.pdf"},"width":345,"height":37},"498E23C82CA78A4BCD7BA88E5243B6FC":{"type":"texture","index":0,"assetRequest":{"type":"slide","state":"contents","slide":"none"},"url":{"native":"assets/3F550030-6477-4261-9B31-014C97946240.pdf"},"width":1024,"height":768}},"events":[{"effects":[{"beginTime":0,"baseLayer":{"animations":[],"initialState":{"affineTransform":[1,0,0,1,0,0],"masksToBounds":false,"rotation":0,"scale":1,"position":{"pointX":512,"pointY":384},"width":1024,"sublayerTransform":[1,0,0,0,0,1,0,0,0,0,1,0,0,0,0,1],"contentsRect":{"y":0,"x":0,"width":1,"height":1},"opacity":1,"edgeAntialiasingMask":251658240,"height":768,"hidden":false,"anchorPoint":{"pointX":0.5,"pointY":0.5}},"objectID":"0","layers":[{"animations":[],"initialState":{"affineTransform":[1,0,0,1,0,0],"masksToBounds":false,"rotation":0,"scale":1,"position":{"pointX":512,"pointY":384},"width":1024,"sublayerTransform":[1,0,0,0,0,1,0,0,0,0,1,-0.0004922987690640373,0,0,0,1],"contentsRect":{"y":0,"x":0,"width":1,"height":1},"opacity":1,"edgeAntialiasingMask":251658240,"height":768,"hidden":false,"anchorPoint":{"pointX":0.5,"pointY":0.5}},"layers":[{"animations":[],"initialState":{"affineTransform":[1,0,0,1,0,0],"masksToBounds":false,"rotation":0,"scale":1,"position":{"pointX":512,"pointY":384},"width":1024,"sublayerTransform":[1,0,0,0,0,1,0,0,0,0,1,0,0,0,0,1],"contentsRect":{"y":0,"x":0,"width":1,"height":1},"opacity":1,"edgeAntialiasingMask":251658240,"height":768,"hidden":false,"anchorPoint":{"pointX":0.5,"pointY":0.5}},"layers":[{"animations":[{"timeOffset":0,"from":{"scalar":false},"beginTime":0,"repeatCount":0,"fillMode":"both","duration":1,"autoreverses":false,"timingFunction":"EaseInEaseOut","property":"hidden","to":{"scalar":false}}],"layers":[],"texturedRectangle":{"isBackgroundTexture":true,"singleTextureOpacity":1,"textureType":1,"textBaseline":0,"textXHeight":0,"isVerticalText":false},"initialState":{"affineTransform":[1,0,0,1,0,0],"masksToBounds":false,"rotation":0,"scale":1,"position":{"pointX":512,"pointY":384},"width":1024,"sublayerTransform":[1,0,0,0,0,1,0,0,0,0,1,0,0,0,0,1],"contentsRect":{"y":0,"x":0,"width":1,"height":1},"opacity":1,"edgeAntialiasingMask":0,"height":768,"hidden":false,"anchorPoint":{"pointX":0.5,"pointY":0.5}},"texture":"498E23C82CA78A4BCD7BA88E5243B6FC"}]},{"animations":[],"initialState":{"affineTransform":[1,0,0,1,0,0],"masksToBounds":false,"rotation":0,"scale":1,"position":{"pointX":512,"pointY":384},"width":1024,"sublayerTransform":[1,0,0,0,0,1,0,0,0,0,1,0,0,0,0,1],"contentsRect":{"y":0,"x":0,"width":1,"height":1},"opacity":1,"edgeAntialiasingMask":251658240,"height":768,"hidden":false,"anchorPoint":{"pointX":0.5,"pointY":0.5}},"layers":[{"animations":[{"timeOffset":0,"from":{"scalar":1},"beginTime":0,"repeatCount":0,"fillMode":"both","duration":1,"autoreverses":false,"timingFunction":"EaseInEaseOut","property":"opacity","to":{"scalar":0}}],"layers":[],"texturedRectangle":{"isBackgroundTexture":true,"singleTextureOpacity":1,"textureType":1,"textBaseline":0,"textXHeight":0,"isVerticalText":false},"initialState":{"affineTransform":[1,0,0,1,0,0],"masksToBounds":false,"rotation":0,"scale":1,"position":{"pointX":512,"pointY":384},"width":1024,"sublayerTransform":[1,0,0,0,0,1,0,0,0,0,1,0,0,0,0,1],"contentsRect":{"y":0,"x":0,"width":1,"height":1},"opacity":1,"edgeAntialiasingMask":0,"height":768,"hidden":false,"anchorPoint":{"pointX":0.5,"pointY":0.5}},"texture":"498E23C82CA78A4BCD7BA88E5243B6FC"}]}]},{"animations":[],"initialState":{"affineTransform":[1,0,0,1,0,0],"masksToBounds":false,"rotation":0,"scale":1,"position":{"pointX":52.93999993801117,"pointY":744},"width":47.87999987602234,"sublayerTransform":[1,0,0,0,0,1,0,0,0,0,1,0,0,0,0,1],"contentsRect":{"y":0,"x":0,"width":1,"height":1},"opacity":1,"edgeAntialiasingMask":251658240,"height":37.00000047683716,"hidden":false,"anchorPoint":{"pointX":0.5,"pointY":0.5}},"layers":[{"animations":[{"timeOffset":0,"beginTime":0,"repeatCount":0,"animations":[{"timeOffset":0,"from":{"pointX":24.5,"pointY":19.00000023841858},"beginTime":0,"repeatCount":0,"fillMode":"both","duration":1,"autoreverses":false,"timingFunction":"EaseInEaseOut","property":"position","to":{"pointX":-2023.5,"pointY":19.00000023841858}},{"timeOffset":0,"from":{"scalar":false},"beginTime":0,"repeatCount":0,"fillMode":"both","property":"hidden","autoreverses":false,"duration":1,"to":{"scalar":false}}],"fillMode":"both","autoreverses":false,"duration":1}],"layers":[],"texturedRectangle":{"singleTextureOpacity":1,"textXHeight":0.303304347826087,"textBaseline":0.6481721193894096,"isBackgroundTexture":true,"isVerticalText":false,"textColor":[0.3747479021549225,0.3747574090957642,0.3747523128986359,1],"textureType":6},"initialState":{"affineTransform":[1,0,0,1,0,0],"masksToBounds":false,"rotation":0,"scale":1,"position":{"pointX":24.5,"pointY":19.00000023841858},"width":43,"sublayerTransform":[1,0,0,0,0,1,0,0,0,0,1,0,0,0,0,1],"contentsRect":{"y":0,"x":0,"width":1,"height":1},"opacity":1,"edgeAntialiasingMask":0,"height":23,"hidden":false,"anchorPoint":{"pointX":0.5,"pointY":0.5}},"texture":"B5EBA366585F3093799141C416FC9441"}]},{"animations":[],"initialState":{"affineTransform":[1,0,0,1,0,0],"masksToBounds":false,"rotation":0,"scale":1,"position":{"pointX":531.4791259765625,"pointY":409.3641052246094},"width":630.2953491210938,"sublayerTransform":[1,0,0,0,0,1,0,0,0,0,1,0,0,0,0,1],"contentsRect":{"y":0,"x":0,"width":1,"height":1},"opacity":1,"edgeAntialiasingMask":251658240,"height":706.9529418945312,"hidden":false,"anchorPoint":{"pointX":0.5,"pointY":0.5}},"layers":[{"animations":[{"timeOffset":0,"beginTime":0,"repeatCount":0,"animations":[{"timeOffset":0,"from":{"pointX":315.1685485839844,"pointY":353.1123657226562},"beginTime":0,"repeatCount":0,"fillMode":"both","duration":1,"autoreverses":false,"timingFunction":"EaseInEaseOut","property":"position","to":{"pointX":-1220.831451416016,"pointY":353.1123657226562}},{"timeOffset":0,"from":{"scalar":false},"beginTime":0,"repeatCount":0,"fillMode":"both","property":"hidden","autoreverses":false,"duration":1,"to":{"scalar":false}}],"fillMode":"both","autoreverses":false,"duration":1}],"layers":[],"texturedRectangle":{"isBackgroundTexture":true,"singleTextureOpacity":1,"textureType":5,"textBaseline":0,"textXHeight":0,"isVerticalText":false},"initialState":{"affineTransform":[1,0,0,1,0,0],"masksToBounds":false,"rotation":0,"scale":1,"position":{"pointX":315.1685485839844,"pointY":353.1123657226562},"width":633,"sublayerTransform":[1,0,0,0,0,1,0,0,0,0,1,0,0,0,0,1],"contentsRect":{"y":0,"x":0,"width":1,"height":1},"opacity":1,"edgeAntialiasingMask":0,"height":710,"hidden":false,"anchorPoint":{"pointX":0.5,"pointY":0.5}},"texture":"9C11DC258698772E4D281BEEDA3F6C41"}]},{"animations":[],"initialState":{"affineTransform":[1,0,0,1,0,0],"masksToBounds":false,"rotation":0,"scale":1,"position":{"pointX":511.5,"pointY":69},"width":951,"sublayerTransform":[1,0,0,0,0,1,0,0,0,0,1,0,0,0,0,1],"contentsRect":{"y":0,"x":0,"width":1,"height":1},"opacity":1,"edgeAntialiasingMask":251658240,"height":138,"hidden":false,"anchorPoint":{"pointX":0.5,"pointY":0.5}},"layers":[{"animations":[{"timeOffset":0,"beginTime":0,"repeatCount":0,"animations":[{"timeOffset":0,"from":{"pointX":242.5,"pointY":69},"beginTime":0,"repeatCount":0,"fillMode":"both","duration":1,"autoreverses":false,"timingFunction":"EaseInEaseOut","property":"position","to":{"pointX":-781.5,"pointY":69}},{"timeOffset":0,"from":{"scalar":false},"beginTime":0,"repeatCount":0,"fillMode":"both","property":"hidden","autoreverses":false,"duration":1,"to":{"scalar":false}}],"fillMode":"both","autoreverses":false,"duration":1}],"layers":[],"texturedRectangle":{"singleTextureOpacity":1,"textXHeight":0.632842105263158,"textBaseline":0.9210526315789473,"isBackgroundTexture":true,"isVerticalText":false,"textColor":[0,0,0,1],"textureType":6},"initialState":{"affineTransform":[1,0,0,1,0,0],"masksToBounds":false,"rotation":0,"scale":1,"position":{"pointX":242.5,"pointY":69},"width":479,"sublayerTransform":[1,0,0,0,0,1,0,0,0,0,1,0,0,0,0,1],"contentsRect":{"y":0,"x":0,"width":1,"height":1},"opacity":1,"edgeAntialiasingMask":0,"height":38,"hidden":false,"anchorPoint":{"pointX":0.5,"pointY":0.5}},"texture":"55C7C75F7F86095E359F538B6151452D"}]},{"animations":[],"initialState":{"affineTransform":[1,0,0,1,0,0],"masksToBounds":false,"rotation":0,"scale":1,"position":{"pointX":52.93999993801117,"pointY":744},"width":47.87999987602234,"sublayerTransform":[1,0,0,0,0,1,0,0,0,0,1,0,0,0,0,1],"contentsRect":{"y":0,"x":0,"width":1,"height":1},"opacity":1,"edgeAntialiasingMask":251658240,"height":37.00000047683716,"hidden":false,"anchorPoint":{"pointX":0.5,"pointY":0.5}},"layers":[{"animations":[{"timeOffset":0,"beginTime":0,"repeatCount":0,"animations":[{"timeOffset":0,"from":{"pointX":1048.5,"pointY":19.00000023841858},"beginTime":0,"repeatCount":0,"fillMode":"both","duration":1,"autoreverses":false,"timingFunction":"EaseInEaseOut","property":"position","to":{"pointX":24.5,"pointY":19.00000023841858}},{"timeOffset":0,"from":{"scalar":false},"beginTime":0,"repeatCount":0,"fillMode":"both","property":"hidden","autoreverses":false,"duration":1,"to":{"scalar":false}}],"fillMode":"both","autoreverses":false,"duration":1}],"layers":[],"texturedRectangle":{"singleTextureOpacity":1,"textXHeight":0.303304347826087,"textBaseline":0.6481721193894096,"isBackgroundTexture":true,"isVerticalText":false,"textColor":[0.3747479021549225,0.3747574090957642,0.3747523128986359,1],"textureType":6},"initialState":{"affineTransform":[1,0,0,1,0,0],"masksToBounds":false,"rotation":0,"scale":1,"position":{"pointX":24.5,"pointY":19.00000023841858},"width":43,"sublayerTransform":[1,0,0,0,0,1,0,0,0,0,1,0,0,0,0,1],"contentsRect":{"y":0,"x":0,"width":1,"height":1},"opacity":1,"edgeAntialiasingMask":0,"height":23,"hidden":true,"anchorPoint":{"pointX":0.5,"pointY":0.5}},"texture":"B5EBA366585F3093799141C416FC9441"}]},{"animations":[],"initialState":{"affineTransform":[1,0,0,1,0,0],"masksToBounds":false,"rotation":0,"scale":1,"position":{"pointX":553.5922241210938,"pointY":383.9999923706055},"width":1383.206176757812,"sublayerTransform":[1,0,0,0,0,1,0,0,0,0,1,0,0,0,0,1],"contentsRect":{"y":0,"x":0,"width":1,"height":1},"opacity":1,"edgeAntialiasingMask":251658240,"height":774.595458984375,"hidden":false,"anchorPoint":{"pointX":0.5,"pointY":0.5}},"layers":[{"animations":[{"timeOffset":0,"beginTime":0,"repeatCount":0,"animations":[{"timeOffset":0,"from":{"pointX":2227.510864257812,"pointY":387.297737121582},"beginTime":0,"repeatCount":0,"fillMode":"both","duration":1,"autoreverses":false,"timingFunction":"EaseInEaseOut","property":"position","to":{"pointX":691.5108642578125,"pointY":387.297737121582}},{"timeOffset":0,"from":{"scalar":false},"beginTime":0,"repeatCount":0,"fillMode":"both","property":"hidden","autoreverses":false,"duration":1,"to":{"scalar":false}}],"fillMode":"both","autoreverses":false,"duration":1}],"layers":[],"texturedRectangle":{"isBackgroundTexture":true,"singleTextureOpacity":1,"textureType":5,"textBaseline":0,"textXHeight":0,"isVerticalText":false},"initialState":{"affineTransform":[1,0,0,1,0,0],"masksToBounds":false,"rotation":0,"scale":1,"position":{"pointX":691.5108642578125,"pointY":387.297737121582},"width":1387,"sublayerTransform":[1,0,0,0,0,1,0,0,0,0,1,0,0,0,0,1],"contentsRect":{"y":0,"x":0,"width":1,"height":1},"opacity":1,"edgeAntialiasingMask":0,"height":778,"hidden":true,"anchorPoint":{"pointX":0.5,"pointY":0.5}},"texture":"3C900D25C5F715D1A9BDACCFBFC181F4"}]},{"animations":[],"initialState":{"affineTransform":[1,0,0,1,0,0],"masksToBounds":false,"rotation":0,"scale":1,"position":{"pointX":511.5,"pointY":69},"width":951,"sublayerTransform":[1,0,0,0,0,1,0,0,0,0,1,0,0,0,0,1],"contentsRect":{"y":0,"x":0,"width":1,"height":1},"opacity":1,"edgeAntialiasingMask":251658240,"height":138,"hidden":false,"anchorPoint":{"pointX":0.5,"pointY":0.5}},"layers":[{"animations":[{"timeOffset":0,"beginTime":0,"repeatCount":0,"animations":[{"timeOffset":0,"from":{"pointX":2223.5,"pointY":68.5},"beginTime":0,"repeatCount":0,"fillMode":"both","duration":1,"autoreverses":false,"timingFunction":"EaseInEaseOut","property":"position","to":{"pointX":175.5,"pointY":68.5}},{"timeOffset":0,"from":{"scalar":false},"beginTime":0,"repeatCount":0,"fillMode":"both","property":"hidden","autoreverses":false,"duration":1,"to":{"scalar":false}}],"fillMode":"both","autoreverses":false,"duration":1}],"layers":[],"texturedRectangle":{"singleTextureOpacity":1,"textXHeight":0.649945945945946,"textBaseline":0.9459459459459459,"isBackgroundTexture":true,"isVerticalText":false,"textColor":[0.9999100565910339,1,0.9998779892921448,1],"textureType":6},"initialState":{"affineTransform":[1,0,0,1,0,0],"masksToBounds":false,"rotation":0,"scale":1,"position":{"pointX":175.5,"pointY":68.5},"width":345,"sublayerTransform":[1,0,0,0,0,1,0,0,0,0,1,0,0,0,0,1],"contentsRect":{"y":0,"x":0,"width":1,"height":1},"opacity":1,"edgeAntialiasingMask":0,"height":37,"hidden":true,"anchorPoint":{"pointX":0.5,"pointY":0.5}},"texture":"F40AA37D961CB1662EDB770BB1B02315"}]}]},"effects":[],"duration":1,"type":"transition","name":"apple:ca-push","objectID":"0"}],"automaticPlay":false,"hyperlinks":[],"accessibility":[{"text":"Start_here.jpg","targetRectangle":{"y":55.88763427734375,"x":216.3314514160156,"width":630.2953491210938,"height":706.9529418945312}},{"text":"It’s a matter of trust.","targetRectangle":{"y":42,"x":40,"width":479.664,"height":55}},{"text":"@jnasr","targetRectangle":{"y":729.4999997615814,"x":33,"width":38.88,"height":29}}],"baseLayer":{"animations":[],"initialState":{"affineTransform":[1,0,0,1,0,0],"masksToBounds":false,"rotation":0,"scale":1,"position":{"pointX":512,"pointY":384},"width":1024,"sublayerTransform":[1,0,0,0,0,1,0,0,0,0,1,0,0,0,0,1],"contentsRect":{"y":0,"x":0,"width":1,"height":1},"opacity":1,"edgeAntialiasingMask":251658240,"height":768,"hidden":false,"anchorPoint":{"pointX":0.5,"pointY":0.5}},"objectID":"0","layers":[{"animations":[],"initialState":{"affineTransform":[1,0,0,1,0,0],"masksToBounds":false,"rotation":0,"scale":1,"position":{"pointX":512,"pointY":384},"width":1024,"sublayerTransform":[1,0,0,0,0,1,0,0,0,0,1,-0.0004922987690640373,0,0,0,1],"contentsRect":{"y":0,"x":0,"width":1,"height":1},"opacity":1,"edgeAntialiasingMask":251658240,"height":768,"hidden":false,"anchorPoint":{"pointX":0.5,"pointY":0.5}},"layers":[{"animations":[],"initialState":{"affineTransform":[1,0,0,1,0,0],"masksToBounds":false,"rotation":0,"scale":1,"position":{"pointX":512,"pointY":384},"width":1024,"sublayerTransform":[1,0,0,0,0,1,0,0,0,0,1,0,0,0,0,1],"contentsRect":{"y":0,"x":0,"width":1,"height":1},"opacity":1,"edgeAntialiasingMask":251658240,"height":768,"hidden":false,"anchorPoint":{"pointX":0.5,"pointY":0.5}},"layers":[{"animations":[],"layers":[],"texturedRectangle":{"isBackgroundTexture":true,"singleTextureOpacity":1,"textureType":1,"textBaseline":0,"textXHeight":0,"isVerticalText":false},"initialState":{"affineTransform":[1,0,0,1,0,0],"masksToBounds":false,"rotation":0,"scale":1,"position":{"pointX":512,"pointY":384},"width":1024,"sublayerTransform":[1,0,0,0,0,1,0,0,0,0,1,0,0,0,0,1],"contentsRect":{"y":0,"x":0,"width":1,"height":1},"opacity":1,"edgeAntialiasingMask":0,"height":768,"hidden":false,"anchorPoint":{"pointX":0.5,"pointY":0.5}},"texture":"498E23C82CA78A4BCD7BA88E5243B6FC"}]},{"animations":[],"initialState":{"affineTransform":[1,0,0,1,0,0],"masksToBounds":false,"rotation":0,"scale":1,"position":{"pointX":512,"pointY":384},"width":1024,"sublayerTransform":[1,0,0,0,0,1,0,0,0,0,1,0,0,0,0,1],"contentsRect":{"y":0,"x":0,"width":1,"height":1},"opacity":1,"edgeAntialiasingMask":251658240,"height":768,"hidden":false,"anchorPoint":{"pointX":0.5,"pointY":0.5}},"layers":[{"animations":[],"layers":[],"texturedRectangle":{"isBackgroundTexture":true,"singleTextureOpacity":1,"textureType":1,"textBaseline":0,"textXHeight":0,"isVerticalText":false},"initialState":{"affineTransform":[1,0,0,1,0,0],"masksToBounds":false,"rotation":0,"scale":1,"position":{"pointX":512,"pointY":384},"width":1024,"sublayerTransform":[1,0,0,0,0,1,0,0,0,0,1,0,0,0,0,1],"contentsRect":{"y":0,"x":0,"width":1,"height":1},"opacity":1,"edgeAntialiasingMask":0,"height":768,"hidden":false,"anchorPoint":{"pointX":0.5,"pointY":0.5}},"texture":"498E23C82CA78A4BCD7BA88E5243B6FC"}]}]},{"animations":[],"initialState":{"affineTransform":[1,0,0,1,0,0],"masksToBounds":false,"rotation":0,"scale":1,"position":{"pointX":52.93999993801117,"pointY":744},"width":47.87999987602234,"sublayerTransform":[1,0,0,0,0,1,0,0,0,0,1,0,0,0,0,1],"contentsRect":{"y":0,"x":0,"width":1,"height":1},"opacity":1,"edgeAntialiasingMask":251658240,"height":37.00000047683716,"hidden":false,"anchorPoint":{"pointX":0.5,"pointY":0.5}},"layers":[{"animations":[],"layers":[],"texturedRectangle":{"singleTextureOpacity":1,"textXHeight":0.303304347826087,"textBaseline":0.6481721193894096,"isBackgroundTexture":true,"isVerticalText":false,"textColor":[0.3747479021549225,0.3747574090957642,0.3747523128986359,1],"textureType":6},"initialState":{"affineTransform":[1,0,0,1,0,0],"masksToBounds":false,"rotation":0,"scale":1,"position":{"pointX":24.5,"pointY":19.00000023841858},"width":43,"sublayerTransform":[1,0,0,0,0,1,0,0,0,0,1,0,0,0,0,1],"contentsRect":{"y":0,"x":0,"width":1,"height":1},"opacity":1,"edgeAntialiasingMask":0,"height":23,"hidden":false,"anchorPoint":{"pointX":0.5,"pointY":0.5}},"texture":"B5EBA366585F3093799141C416FC9441"}]},{"animations":[],"initialState":{"affineTransform":[1,0,0,1,0,0],"masksToBounds":false,"rotation":0,"scale":1,"position":{"pointX":531.4791259765625,"pointY":409.3641052246094},"width":630.2953491210938,"sublayerTransform":[1,0,0,0,0,1,0,0,0,0,1,0,0,0,0,1],"contentsRect":{"y":0,"x":0,"width":1,"height":1},"opacity":1,"edgeAntialiasingMask":251658240,"height":706.9529418945312,"hidden":false,"anchorPoint":{"pointX":0.5,"pointY":0.5}},"layers":[{"animations":[],"layers":[],"texturedRectangle":{"isBackgroundTexture":true,"singleTextureOpacity":1,"textureType":5,"textBaseline":0,"textXHeight":0,"isVerticalText":false},"initialState":{"affineTransform":[1,0,0,1,0,0],"masksToBounds":false,"rotation":0,"scale":1,"position":{"pointX":315.1685485839844,"pointY":353.1123657226562},"width":633,"sublayerTransform":[1,0,0,0,0,1,0,0,0,0,1,0,0,0,0,1],"contentsRect":{"y":0,"x":0,"width":1,"height":1},"opacity":1,"edgeAntialiasingMask":0,"height":710,"hidden":false,"anchorPoint":{"pointX":0.5,"pointY":0.5}},"texture":"9C11DC258698772E4D281BEEDA3F6C41"}]},{"animations":[],"initialState":{"affineTransform":[1,0,0,1,0,0],"masksToBounds":false,"rotation":0,"scale":1,"position":{"pointX":511.5,"pointY":69},"width":951,"sublayerTransform":[1,0,0,0,0,1,0,0,0,0,1,0,0,0,0,1],"contentsRect":{"y":0,"x":0,"width":1,"height":1},"opacity":1,"edgeAntialiasingMask":251658240,"height":138,"hidden":false,"anchorPoint":{"pointX":0.5,"pointY":0.5}},"layers":[{"animations":[],"layers":[],"texturedRectangle":{"singleTextureOpacity":1,"textXHeight":0.632842105263158,"textBaseline":0.9210526315789473,"isBackgroundTexture":true,"isVerticalText":false,"textColor":[0,0,0,1],"textureType":6},"initialState":{"affineTransform":[1,0,0,1,0,0],"masksToBounds":false,"rotation":0,"scale":1,"position":{"pointX":242.5,"pointY":69},"width":479,"sublayerTransform":[1,0,0,0,0,1,0,0,0,0,1,0,0,0,0,1],"contentsRect":{"y":0,"x":0,"width":1,"height":1},"opacity":1,"edgeAntialiasingMask":0,"height":38,"hidden":false,"anchorPoint":{"pointX":0.5,"pointY":0.5}},"texture":"55C7C75F7F86095E359F538B6151452D"}]},{"animations":[],"initialState":{"affineTransform":[1,0,0,1,0,0],"masksToBounds":false,"rotation":0,"scale":1,"position":{"pointX":52.93999993801117,"pointY":744},"width":47.87999987602234,"sublayerTransform":[1,0,0,0,0,1,0,0,0,0,1,0,0,0,0,1],"contentsRect":{"y":0,"x":0,"width":1,"height":1},"opacity":1,"edgeAntialiasingMask":251658240,"height":37.00000047683716,"hidden":false,"anchorPoint":{"pointX":0.5,"pointY":0.5}},"layers":[{"animations":[],"layers":[],"texturedRectangle":{"singleTextureOpacity":1,"textXHeight":0.303304347826087,"textBaseline":0.6481721193894096,"isBackgroundTexture":true,"isVerticalText":false,"textColor":[0.3747479021549225,0.3747574090957642,0.3747523128986359,1],"textureType":6},"initialState":{"affineTransform":[1,0,0,1,0,0],"masksToBounds":false,"rotation":0,"scale":1,"position":{"pointX":24.5,"pointY":19.00000023841858},"width":43,"sublayerTransform":[1,0,0,0,0,1,0,0,0,0,1,0,0,0,0,1],"contentsRect":{"y":0,"x":0,"width":1,"height":1},"opacity":1,"edgeAntialiasingMask":0,"height":23,"hidden":true,"anchorPoint":{"pointX":0.5,"pointY":0.5}},"texture":"B5EBA366585F3093799141C416FC9441"}]},{"animations":[],"initialState":{"affineTransform":[1,0,0,1,0,0],"masksToBounds":false,"rotation":0,"scale":1,"position":{"pointX":553.5922241210938,"pointY":383.9999923706055},"width":1383.206176757812,"sublayerTransform":[1,0,0,0,0,1,0,0,0,0,1,0,0,0,0,1],"contentsRect":{"y":0,"x":0,"width":1,"height":1},"opacity":1,"edgeAntialiasingMask":251658240,"height":774.595458984375,"hidden":false,"anchorPoint":{"pointX":0.5,"pointY":0.5}},"layers":[{"animations":[],"layers":[],"texturedRectangle":{"isBackgroundTexture":true,"singleTextureOpacity":1,"textureType":5,"textBaseline":0,"textXHeight":0,"isVerticalText":false},"initialState":{"affineTransform":[1,0,0,1,0,0],"masksToBounds":false,"rotation":0,"scale":1,"position":{"pointX":691.5108642578125,"pointY":387.297737121582},"width":1387,"sublayerTransform":[1,0,0,0,0,1,0,0,0,0,1,0,0,0,0,1],"contentsRect":{"y":0,"x":0,"width":1,"height":1},"opacity":1,"edgeAntialiasingMask":0,"height":778,"hidden":true,"anchorPoint":{"pointX":0.5,"pointY":0.5}},"texture":"3C900D25C5F715D1A9BDACCFBFC181F4"}]},{"animations":[],"initialState":{"affineTransform":[1,0,0,1,0,0],"masksToBounds":false,"rotation":0,"scale":1,"position":{"pointX":511.5,"pointY":69},"width":951,"sublayerTransform":[1,0,0,0,0,1,0,0,0,0,1,0,0,0,0,1],"contentsRect":{"y":0,"x":0,"width":1,"height":1},"opacity":1,"edgeAntialiasingMask":251658240,"height":138,"hidden":false,"anchorPoint":{"pointX":0.5,"pointY":0.5}},"layers":[{"animations":[],"layers":[],"texturedRectangle":{"singleTextureOpacity":1,"textXHeight":0.649945945945946,"textBaseline":0.9459459459459459,"isBackgroundTexture":true,"isVerticalText":false,"textColor":[0.9999100565910339,1,0.9998779892921448,1],"textureType":6},"initialState":{"affineTransform":[1,0,0,1,0,0],"masksToBounds":false,"rotation":0,"scale":1,"position":{"pointX":175.5,"pointY":68.5},"width":345,"sublayerTransform":[1,0,0,0,0,1,0,0,0,0,1,0,0,0,0,1],"contentsRect":{"y":0,"x":0,"width":1,"height":1},"opacity":1,"edgeAntialiasingMask":0,"height":37,"hidden":true,"anchorPoint":{"pointX":0.5,"pointY":0.5}},"texture":"F40AA37D961CB1662EDB770BB1B02315"}]}]}}]}